cloudgeass/__init__.py
cloudgeass/aws/__init__.py
cloudgeass/aws/ec2.py
cloudgeass/aws/lambda.py
cloudgeass/aws/s3.py
cloudgeass/aws/secrets.py
cloudgeass/utils/__init__.py
cloudgeass/utils/log.py
cloudgeass/utils/prep.py
tests/__init__.py
tests/conftest.py
tests/test_ec2.py
tests/test_s3.py
tests/test_secrets.py
tests/test_utils_log.py
tests/test_utils_prep.py
tests/helpers/__init__.py
tests/helpers/faker.py
tests/helpers/user_inputs.py
cloudgeass-2.0.1.dist-info/LICENSE
cloudgeass-2.0.1.dist-info/METADATA
cloudgeass-2.0.1.dist-info/WHEEL
cloudgeass-2.0.1.dist-info/top_level.txt
cloudgeass-2.0.1.dist-info/RECORD
