Metadata-Version: 2.1
Name: cloudgeass
Version: 2.0.1
Summary: Making your life easier on doing simple tasks in AWS via boto3
Home-page: https://github.com/ThiagoPanini/cloudgeass
Author: Thiago Panini
Author-email: panini.development@gmail.com
License: MIT
Keywords: Cloud,AWS,Python,boto3
Classifier: Programming Language :: Python :: 3
Classifier: Development Status :: 4 - Beta
Classifier: Intended Audience :: Developers
Classifier: Natural Language :: Portuguese (Brazilian)
Classifier: License :: OSI Approved :: MIT License
Classifier: Operating System :: OS Independent
Classifier: Programming Language :: Python :: 3.7
Classifier: Programming Language :: Python :: 3.8
Classifier: Programming Language :: Python :: 3.9
Classifier: Programming Language :: Python :: 3.10
Classifier: Topic :: Software Development :: Libraries :: Python Modules
Requires-Python: >=3.0.0
License-File: LICENSE
Requires-Dist: boto3
Requires-Dist: Faker
Requires-Dist: pyarrow
